[{"index":0,"tokens":[{"text":"Upphitun","lemma":"upphitun","pos":"nven"},{"text":"fyrir","lemma":"fyrir","pos":"ao"},{"text":"barnamót","lemma":"barnamót","pos":"nheo"},{"text":"í","lemma":"í","pos":"aþ"},{"text":"Blönduósi","lemma":"Blönduós","pos":"nkeþs"}]},{"index":1,"tokens":[{"text":"Listasýning","lemma":"listasýning","pos":"nven"},{"text":"heiðursgests","lemma":"heiðursgestur","pos":"nkees"},{"text":"á","lemma":"á","pos":"aþ"},{"text":"Safnahúsinu","lemma":"safnahús","pos":"nheþg"}]},{"index":2,"tokens":[{"text":"Áhugamenn","lemma":"áhugi","pos":"nkfn"},{"text":"um","lemma":"um","pos":"ao"},{"text":"skipulagðar","lemma":"skipuleggja","pos":"sþgvfn"},{"text":"göngutúr","lemma":"göngutúr","pos":"nkfo"},{"text":"í","lemma":"í","pos":"aþ"},{"text":"Húnavatnssýslu","lemma":"Húnavatnssýsla","pos":"nvees"}]},{"index":3,"tokens":[{"text":"Samningur","lemma":"samningur","pos":"nken"},{"text":"um","lemma":"um","pos":"ao"},{"text":"nýja","lemma":"nýr","pos":"lveosf"},{"text":"sundlaug","lemma":"sundlaug","pos":"nveo"},{"text":"í","lemma":"í","pos":"aþ"},{"text":"Blönduósi","lemma":"Blönduós","pos":"nkeþs"},{"text":"samþykktur","lemma":"samþykkja","pos":"sþgken"}]},{"index":4,"tokens":[{"text":"Framlag","lemma":"framlag","pos":"nhen"},{"text":"úr","lemma":"úr","pos":"aþ"},{"text":"sjóður","lemma":"sjóður","pos":"nkeþ"},{"text":"Húnvetninga","lemma":"Húnvetningur","pos":"nkfes"},{"text":"til","lemma":"til","pos":"ae"},{"text":"íþrótta","lemma":"íþrótt","pos":"nvfes"}]},{"index":5,"tokens":[{"text":"Félagsmiðstöð","lemma":"félagsmiðstöð","pos":"nven"},{"text":"Blönduóss","lemma":"Blönduós","pos":"nkees"},{"text":"opnar","lemma":"opna","pos":"sfg3en"},{"text":"dyrnar","lemma":"dyr","pos":"nvfog"}]},{"index":6,"tokens":[{"text":"Upphaf","lemma":"upphaf","pos":"nhen"},{"text":"nýs","lemma":"nýr","pos":"lhеesf"},{"text":"tímabils","lemma":"tímabil","pos":"nhees"},{"text":"hjá","lemma":"hjá","pos":"aþ"},{"text":"Blönduskóla","lemma":"Blönduskóli","pos":"nkeþs"}]},{"index":7,"tokens":[{"text":"Markverðar","lemma":"markverður","pos":"lvfnosf"},{"text":"niðurstöður","lemma":"niðurstaða","pos":"nvfn"},{"text":"í","lemma":"í","pos":"aþ"},{"text":"skoðanakönnun","lemma":"skoðanakönnun","pos":"nveþ"},{"text":"um","lemma":"um","pos":"ao"},{"text":"umhverfismál","lemma":"umhverfismál","pos":"nhfo"}]},{"index":8,"tokens":[{"text":"Skipulagðir","lemma":"skipuleggja","pos":"sþgkfn"},{"text":"göngutúr","lemma":"göngutúr","pos":"nkfn"},{"text":"um","lemma":"um","pos":"ao"},{"text":"Blönduós","lemma":"Blönduós","pos":"nkeos"},{"text":"og","lemma":"og","pos":"c"},{"text":"nágrenni","lemma":"nágrenni","pos":"nheo"}]},{"index":9,"tokens":[{"text":"Tónlistarfræðsla","lemma":"tónlistarfræðsla","pos":"nven"},{"text":"fyrir","lemma":"fyrir","pos":"ao"},{"text":"unga","lemma":"ungur","pos":"lhfosf"},{"text":"fólk","lemma":"fólk","pos":"nheo"},{"text":"í","lemma":"í","pos":"aþ"},{"text":"Húnavatnssýslu","lemma":"Húnavatnssýsla","pos":"nvees"}]},{"index":10,"tokens":[{"text":"Samningar","lemma":"samningur","pos":"nkfn"},{"text":"um","lemma":"um","pos":"ao"},{"text":"nýtt","lemma":"nýr","pos":"lhenosf"},{"text":"sundhöll","lemma":"sundhöll","pos":"nven"},{"text":"nálægt","lemma":"nálægt","pos":"ao"},{"text":"Blönduósi","lemma":"Blönduós","pos":"nkeþs"}]},{"index":11,"tokens":[{"text":"Framlag","lemma":"framlag","pos":"nhen"},{"text":"úr","lemma":"úr","pos":"aþ"},{"text":"Húnavatnsbúnaðarsjóði","lemma":"Húnavatnsbúnaðarsjóður","pos":"nkeþ"},{"text":"til","lemma":"til","pos":"ae"},{"text":"ungmennaíþrótta","lemma":"ungmennaíþrótt","pos":"nvfes"}]},{"index":12,"tokens":[{"text":"Aðalfundur","lemma":"aðalfundur","pos":"nken"},{"text":"Húnvetnaframtaks","lemma":"Húnvetnaframtak","pos":"nhees"},{"text":"haldinn","lemma":"halda","pos":"sþgken"},{"text":"í","lemma":"í","pos":"aþ"},{"text":"kvöld","lemma":"kvöld","pos":"nheþ"}]},{"index":13,"tokens":[{"text":"Nýtt","lemma":"nýr","pos":"lhenosf"},{"text":"stærsta","lemma":"stór","pos":"lheosm"},{"text":"verkefni","lemma":"verkefni","pos":"nhen"},{"text":"í","lemma":"í","pos":"aþ"},{"text":"Húnaþingi","lemma":"Húnaþing","pos":"nheþs"},{"text":"samþykkt","lemma":"samþykkja","pos":"sþghen"}]},{"index":14,"tokens":[{"text":"Framlag","lemma":"framlag","pos":"nhen"},{"text":"úr","lemma":"úr","pos":"aþ"},{"text":"sjóðum","lemma":"sjóður","pos":"nkfþ"},{"text":"til","lemma":"til","pos":"ae"},{"text":"atvinnulífs","lemma":"atvinnulíf","pos":"nhees"},{"text":"á","lemma":"á","pos":"aþ"},{"text":"Blönduósi","lemma":"Blönduós","pos":"nkeþs"}]},{"index":15,"tokens":[{"text":"Upphitun","lemma":"upphitun","pos":"nven"},{"text":"fyrir","lemma":"fyrir","pos":"ao"},{"text":"skóla","lemma":"skóli","pos":"nkfo"},{"text":"í","lemma":"í","pos":"aþ"},{"text":"Húnavatnssýslu","lemma":"Húnavatnssýsla","pos":"nvees"},{"text":"fer","lemma":"fara","pos":"sfg3en"},{"text":"fram","lemma":"fram","pos":"aa"},{"text":"í","lemma":"í","pos":"aþ"},{"text":"dag","lemma":"dagur","pos":"nkeþ"}]},{"index":16,"tokens":[{"text":"Fundur","lemma":"fundur","pos":"nken"},{"text":"um","lemma":"um","pos":"ao"},{"text":"nýja","lemma":"nýr","pos":"lveosf"},{"text":"samgönguáætlun","lemma":"samgönguáætlun","pos":"nveo"},{"text":"í","lemma":"í","pos":"aþ"},{"text":"Húnaþingi","lemma":"Húnaþing","pos":"nheþs"}]},{"index":17,"tokens":[{"text":"Framlag","lemma":"framlag","pos":"nhen"},{"text":"úr","lemma":"úr","pos":"aþ"},{"text":"sjóðum","lemma":"sjóður","pos":"nkfþ"},{"text":"til","lemma":"til","pos":"ae"},{"text":"félagsstarfs","lemma":"félagsstarf","pos":"nhees"},{"text":"í","lemma":"í","pos":"aþ"},{"text":"Blönduósi","lemma":"Blönduós","pos":"nkeþs"}]},{"index":18,"tokens":[{"text":"Aðalfundur","lemma":"aðalfundur","pos":"nken"},{"text":"Héraðsskólans","lemma":"héraðsskóli","pos":"nkeeg"},{"text":"haldinn","lemma":"halda","pos":"sþgken"},{"text":"í","lemma":"í","pos":"aþ"},{"text":"kvöld","lemma":"kvöld","pos":"nheþ"}]},{"index":19,"tokens":[{"text":"Nýr","lemma":"nýr","pos":"lkenosf"},{"text":"formaður","lemma":"formaður","pos":"nken"},{"text":"kjörinn","lemma":"kjósa","pos":"sþgken"},{"text":"í","lemma":"í","pos":"aþ"},{"text":"Húnvetnasambandi","lemma":"Húnvetnasamband","pos":"nheþ"}]},{"index":20,"tokens":[{"text":"Framlag","lemma":"framlag","pos":"nhen"},{"text":"úr","lemma":"úr","pos":"aþ"},{"text":"sjóðum","lemma":"sjóður","pos":"nkfþ"},{"text":"til","lemma":"til","pos":"ae"},{"text":"menningarstarfs","lemma":"menningastarf","pos":"nhees"},{"text":"í","lemma":"í","pos":"aþ"},{"text":"Húnaþingi","lemma":"Húnaþing","pos":"nheþs"}]},{"index":21,"tokens":[{"text":"Upphitun","lemma":"upphitun","pos":"nven"},{"text":"fyrir","lemma":"fyrir","pos":"ao"},{"text":"sumarhátíð","lemma":"sumarhátíð","pos":"nveo"},{"text":"í","lemma":"í","pos":"aþ"},{"text":"Blönduósi","lemma":"Blönduós","pos":"nkeþs"},{"text":"fer","lemma":"fara","pos":"sfg3en"},{"text":"fram","lemma":"fram","pos":"aa"},{"text":"í","lemma":"í","pos":"aþ"},{"text":"kvöld","lemma":"kvöld","pos":"nheþ"}]},{"index":22,"tokens":[{"text":"Framlag","lemma":"framlag","pos":"nhen"},{"text":"úr","lemma":"úr","pos":"aþ"},{"text":"sjóðum","lemma":"sjóður","pos":"nkfþ"},{"text":"til","lemma":"til","pos":"ae"},{"text":"íþrótta","lemma":"íþrótt","pos":"nvfes"},{"text":"og","lemma":"og","pos":"c"},{"text":"ungmennaverksmiðju","lemma":"ungmennaverksmiðja","pos":"nveес"}]},{"index":23,"tokens":[{"text":"Aðalfundur","lemma":"aðalfundur","pos":"nken"},{"text":"Húnavatnsbúnaðarsambands","lemma":"Húnavatnsbúnaðarsamband","pos":"nheеs"},{"text":"haldinn","lemma":"halda","pos":"sþgken"},{"text":"í","lemma":"í","pos":"aþ"},{"text":"kvöld","lemma":"kvöld","pos":"nheþ"}]},{"index":24,"tokens":[{"text":"Nýr","lemma":"nýr","pos":"lkenosf"},{"text":"samningur","lemma":"samningur","pos":"nken"},{"text":"um","lemma":"um","pos":"ao"},{"text":"heilsuhæli","lemma":"heilsuhæli","pos":"nheo"},{"text":"í","lemma":"í","pos":"aþ"},{"text":"Húnaþingi","lemma":"Húnaþing","pos":"nheþs"},{"text":"samþykktur","lemma":"samþykkja","pos":"sþgken"}]},{"index":25,"tokens":[{"text":"Framlag","lemma":"framlag","pos":"nhen"},{"text":"úr","lemma":"úr","pos":"aþ"},{"text":"sjóðum","lemma":"sjóður","pos":"nkfþ"},{"text":"til","lemma":"til","pos":"ae"},{"text":"umhverfisverkefna","lemma":"umhverfisverkefni","pos":"nhfes"},{"text":"í","lemma":"í","pos":"aþ"},{"text":"Blönduósi","lemma":"Blönduós","pos":"nkeþs"}]},{"index":26,"tokens":[{"text":"Upphitun","lemma":"upphitun","pos":"nven"},{"text":"fyrir","lemma":"fyrir","pos":"ao"},{"text":"nýtt","lemma":"nýr","pos":"lheosf"},{"text":"tímabil","lemma":"tímabil","pos":"nheo"},{"text":"í","lemma":"í","pos":"aþ"},{"text":"Húnavatnsskóla","lemma":"Húnavatnsskóli","pos":"nkeþs"}]},{"index":27,"tokens":[{"text":"Framlag","lemma":"framlag","pos":"nhen"},{"text":"úr","lemma":"úr","pos":"aþ"},{"text":"sjóðum","lemma":"sjóður","pos":"nkfþ"},{"text":"til","lemma":"til","pos":"ae"},{"text":"félagsmála","lemma":"félagsmál","pos":"nhfes"},{"text":"í","lemma":"í","pos":"aþ"},{"text":"Húnaþingi","lemma":"Húnaþing","pos":"nheþs"}]},{"index":28,"tokens":[{"text":"Aðalfundur","lemma":"aðalfundur","pos":"nken"},{"text":"Húnvetnafélags","lemma":"Húnvetnafélag","pos":"nhees"},{"text":"haldinn","lemma":"halda","pos":"sþgken"},{"text":"í","lemma":"í","pos":"aþ"},{"text":"kvöld","lemma":"kvöld","pos":"nheþ"}]},{"index":29,"tokens":[{"text":"Nýr","lemma":"nýr","pos":"lkenosf"},{"text":"samningur","lemma":"samningur","pos":"nken"},{"text":"um","lemma":"um","pos":"ao"},{"text":"íþróttahús","lemma":"íþróttahús","pos":"nheo"},{"text":"samþykktur","lemma":"samþykkja","pos":"sþgken"}]},{"index":30,"tokens":[{"text":"Framlag","lemma":"framlag","pos":"nhen"},{"text":"úr","lemma":"úr","pos":"aþ"},{"text":"sjóðum","lemma":"sjóður","pos":"nkfþ"},{"text":"til","lemma":"til","pos":"ae"},{"text":"menningarstarfs","lemma":"menningastarf","pos":"nhees"},{"text":"í","lemma":"í","pos":"aþ"},{"text":"Blönduósi","lemma":"Blönduós","pos":"nkeþs"}]},{"index":31,"tokens":[{"text":"Upphitun","lemma":"upphitun","pos":"nven"},{"text":"fyrir","lemma":"fyrir","pos":"ao"},{"text":"sumardvöl","lemma":"sumardvöl","pos":"nveo"},{"text":"í","lemma":"í","pos":"aþ"},{"text":"Húnavatnssýslu","lemma":"Húnavatnssýsla","pos":"nvees"}]},{"index":32,"tokens":[{"text":"Framlag","lemma":"framlag","pos":"nhen"},{"text":"úr","lemma":"úr","pos":"aþ"},{"text":"sjóðum","lemma":"sjóður","pos":"nkfþ"},{"text":"til","lemma":"til","pos":"ae"},{"text":"atvinnulífs","lemma":"atvinnulíf","pos":"nhees"},{"text":"í","lemma":"í","pos":"aþ"},{"text":"Húnaþingi","lemma":"Húnaþing","pos":"nheþs"}]},{"index":33,"tokens":[{"text":"Aðalfundur","lemma":"aðalfundur","pos":"nken"},{"text":"Héraðsskólans","lemma":"héraðsskóli","pos":"nkeeg"},{"text":"haldinn","lemma":"halda","pos":"sþgken"},{"text":"í","lemma":"í","pos":"aþ"},{"text":"kvöld","lemma":"kvöld","pos":"nheþ"}]},{"index":34,"tokens":[{"text":"Nýr","lemma":"nýr","pos":"lkenosf"},{"text":"formaður","lemma":"formaður","pos":"nken"},{"text":"kjörinn","lemma":"kjósa","pos":"sþgken"},{"text":"í","lemma":"í","pos":"aþ"},{"text":"Húnvetnafélagi","lemma":"Húnvetnafélag","pos":"nheþ"}]},{"index":35,"tokens":[{"text":"Framlag","lemma":"framlag","pos":"nhen"},{"text":"úr","lemma":"úr","pos":"aþ"},{"text":"sjóðum","lemma":"sjóður","pos":"nkfþ"},{"text":"til","lemma":"til","pos":"ae"},{"text":"félagsstarfs","lemma":"félagsstarf","pos":"nhees"},{"text":"í","lemma":"í","pos":"aþ"},{"text":"Blönduósi","lemma":"Blönduós","pos":"nkeþs"}]},{"index":36,"tokens":[{"text":"Upphitun","lemma":"upphitun","pos":"nven"},{"text":"fyrir","lemma":"fyrir","pos":"ao"},{"text":"nýtt","lemma":"nýr","pos":"lheosf"},{"text":"tímabil","lemma":"tímabil","pos":"nheo"},{"text":"í","lemma":"í","pos":"aþ"},{"text":"Húnavatnsskóla","lemma":"Húnavatnsskóli","pos":"nkeþs"}]},{"index":37,"tokens":[{"text":"Framlag","lemma":"framlag","pos":"nhen"},{"text":"úr","lemma":"úr","pos":"aþ"},{"text":"sjóðum","lemma":"sjóður","pos":"nkfþ"},{"text":"til","lemma":"til","pos":"ae"},{"text":"umhverfisverkefna","lemma":"umhverfisverkefni","pos":"nhfes"},{"text":"í","lemma":"í","pos":"aþ"},{"text":"Húnaþingi","lemma":"Húnaþing","pos":"nheþs"}]},{"index":38,"tokens":[{"text":"Aðalfundur","lemma":"aðalfundur","pos":"nken"},{"text":"Húnavatnsbúnaðarsambands","lemma":"Húnavatnsbúnaðarsamband","pos":"nhees"},{"text":"haldinn","lemma":"halda","pos":"sþgken"},{"text":"í","lemma":"í","pos":"aþ"},{"text":"kvöld","lemma":"kvöld","pos":"nheþ"}]},{"index":39,"tokens":[{"text":"Nýr","lemma":"nýr","pos":"lkenosf"},{"text":"samningur","lemma":"samningur","pos":"nken"},{"text":"um","lemma":"um","pos":"ao"},{"text":"heilsuhæli","lemma":"heilsuhæli","pos":"nheo"},{"text":"samþykktur","lemma":"samþykkja","pos":"sþgken"}]}]